uvcclient/__init__.py
uvcclient/camera.py
uvcclient/const.py
uvcclient/main.py
uvcclient/nvr.py
uvcclient/py.typed
uvcclient/store.py
uvcclient-0.12.2.dist-info/LICENSE
uvcclient-0.12.2.dist-info/METADATA
uvcclient-0.12.2.dist-info/WHEEL
uvcclient-0.12.2.dist-info/entry_points.txt
uvcclient-0.12.2.dist-info/RECORD
