Metadata-Version: 2.1
Name: uvcclient
Version: 0.12.2
Summary: A remote control client for Ubiquiti's UVC NVR
Home-page: https://github.com/uilibs/uvcclient
Author: Dan Smith
Author-email: dsmith+uvcclient@danplanet.com
Requires-Python: >=3.10
Classifier: Development Status :: 5 - Production/Stable
Classifier: Intended Audience :: Developers
Classifier: License :: OSI Approved :: GNU General Public License v3 (GPLv3)
Classifier: Natural Language :: English
Classifier: Operating System :: OS Independent
Classifier: Programming Language :: Python :: 3
Classifier: Programming Language :: Python :: 3.10
Classifier: Programming Language :: Python :: 3.11
Classifier: Programming Language :: Python :: 3.12
Classifier: Topic :: Software Development :: Build Tools
Classifier: Topic :: Software Development :: Libraries
Classifier: Typing :: Typed
Project-URL: Bug Tracker, https://github.com/uilibs/uvcclient/issues
Project-URL: Changelog, https://github.com/uilibs/uvcclient/blob/main/CHANGELOG.md
Project-URL: Repository, https://github.com/uilibs/uvcclient
